mobot_utils/__init__.py
mobot_utils/disp_cam.py
mobot_utils/teleop.py
mobot_utils-0.1.2.dist-info/METADATA
mobot_utils-0.1.2.dist-info/WHEEL
mobot_utils-0.1.2.dist-info/entry_points.txt
mobot_utils-0.1.2.dist-info/top_level.txt
mobot_utils-0.1.2.dist-info/RECORD
